[
	{
		"title": "Момчето си отива",
		"thumbnail_name": "momcheto_image",
		"video_id": "_uuhDvvY1_Q",
		"duration": "101",
		"release_year": "1972",
		"director": "Людмил Кирков"
	},
	{
		"title": "Господин за един ден",
		"thumbnail_name": "gospodin_image",
		"video_id": "evqlOa5youA",
		"duration": "87",
		"release_year": "1983",
		"director": "Николай Волев"
	},
	{
		"title": "Време разделно",
		"thumbnail_name": "vreme_razdelno_image",
		"video_id": "UCWF9ZJ-ibY",
		"duration": "267",
		"release_year": "1988",
		"director": "Людмил Стайков"
	},
	{
		"title": "Козият рог",
		"thumbnail_name": "kozijat_rog_image",
		"video_id": "kHE2qQuLHy4",
		"duration": "91",
		"release_year": "1972",
		"director": "Методи Андонов"
	},
	{
		"title": "Да обичаш на инат",
		"thumbnail_name": "inat_image",
		"video_id": "1PHqIndDyTI",
		"duration": "92",
		"release_year": "1986",
		"director": "Николай Волев"
	},
	{
		"title": "Крадецът на праскови",
		"thumbnail_name": "kradec_image",
		"video_id": "7kwmpkXH2Nc",
		"duration": 79,
		"release_year": 1964,
		"director": "Въло Радев"
	},
	{
		"title": "Двойникът",
		"thumbnail_name": "dvoinik_image",
		"video_id": "1N7wAD5UkKQ",
		"duration": 98,
		"release_year": 1980,
		"director": "Николай Волев"
	},
	{
		"title": "Любимец 13",
		"thumbnail_name": "lubimec_image",
		"video_id": "aSOp9XhySyM",
		"duration": 89,
		"release_year": 1958,
		"director": "Владимир Янчев"
	},
	{
		"title": "Баш майсторът",
		"thumbnail_name": "maistor_image",
		"video_id": "qbe3WrXl5sM",
		"duration": 65,
		"release_year": 1973,
		"director": "Петър Василев"
	},
	{
		"title": "Свобода или смърт",
		"thumbnail_name": "svoboda_smart_image",
		"video_id": "v2c--Ir1KNc",
		"movieDescription": "test"
	},
	{
		"title": "С деца на море",
		"thumbnail_name": "deca_na_more_image",
		"video_id": "AqK_BACqmjo",
		"movieDescription": "test"
	},
	{
		"title": "Куче в чекмедже",
		"thumbnail_name": "kuche_image",
		"video_id": "UyKmIsS8bTU",
		"movieDescription": "test"
	},
	{
		"title": "Хитър Петър",
		"thumbnail_name": "hitur_petur_image",
		"video_id": "rzS1OqsB3gw",
		"movieDescription": "test"
	}
]
